letschatty/__init__.py
letschatty/models/__init__.py
letschatty/models/ai_microservices/__init__.py
letschatty/models/ai_microservices/expected_output.py
letschatty/models/ai_microservices/lambda_events.py
letschatty/models/ai_microservices/lambda_invokation_types.py
letschatty/models/ai_microservices/n8n_ai_agents_payload.py
letschatty/models/ai_microservices/openai_payloads.py
letschatty/models/analytics/__init__.py
letschatty/models/analytics/events/__init__.py
letschatty/models/analytics/events/base.py
letschatty/models/analytics/events/chat_based_events/ai_agent_chat.py
letschatty/models/analytics/events/chat_based_events/ai_agent_execution_event.py
letschatty/models/analytics/events/chat_based_events/business_area.py
letschatty/models/analytics/events/chat_based_events/chat_based_event.py
letschatty/models/analytics/events/chat_based_events/chat_context.py
letschatty/models/analytics/events/chat_based_events/chat_funnel.py
letschatty/models/analytics/events/chat_based_events/chat_status.py
letschatty/models/analytics/events/chat_based_events/contact_point.py
letschatty/models/analytics/events/chat_based_events/continuous_conversation.py
letschatty/models/analytics/events/chat_based_events/highlight.py
letschatty/models/analytics/events/chat_based_events/message.py
letschatty/models/analytics/events/chat_based_events/messages_intent_context.py
letschatty/models/analytics/events/chat_based_events/product_chat.py
letschatty/models/analytics/events/chat_based_events/quality_scoring.py
letschatty/models/analytics/events/chat_based_events/sale.py
letschatty/models/analytics/events/chat_based_events/tag_chat.py
letschatty/models/analytics/events/chat_based_events/workflow.py
letschatty/models/analytics/events/company_based_events/asset_events.py
letschatty/models/analytics/events/company_based_events/company_events.py
letschatty/models/analytics/events/company_based_events/user_events.py
letschatty/models/analytics/events/event_type_to_classes.py
letschatty-0.4.350.dist-info/LICENSE
letschatty-0.4.350.dist-info/METADATA
letschatty-0.4.350.dist-info/WHEEL
letschatty-0.4.350.dist-info/RECORD
